<bill session="119" type="h" number="6671" updated="2025-12-12T09:07:22Z">
  <state datetime="2025-12-11">REFERRED</state>
  <status>
    <introduced datetime="2025-12-11"/>
  </status>
  <introduced datetime="2025-12-11"/>
  <titles>
    <title type="display">To reauthorize and improve the reconnecting communities program, and for other purposes.</title>
    <title type="official" as="introduced">To reauthorize and improve the reconnecting communities program, and for other purposes.</title>
  </titles>
  <sponsor bioguide_id="R000579"/>
  <cosponsors>
    <cosponsor bioguide_id="F000481" joined="2025-12-11"/>
  </cosponsors>
  <actions>
    <action datetime="2025-12-11">
      <text>Introduced in House</text>
    </action>
    <action datetime="2025-12-11" state="REFERRED">
      <text>Referred to the House Committee on Transportation and Infrastructure.</text>
    </action>
  </actions>
  <committees>
    <committee code="HSPW" name="House Transportation and Infrastructure" subcommittee="" activity="Referred To"/>
  </committees>
  <relatedbills/>
  <subjects/>
  <amendments/>
</bill>
