<bill session="119" type="h" number="7012" updated="2026-02-02T22:08:17Z">
  <state datetime="2026-01-12">REFERRED</state>
  <status>
    <introduced datetime="2026-01-12"/>
  </status>
  <introduced datetime="2026-01-12"/>
  <titles>
    <title type="display">Greenland Annexation and Statehood Act</title>
    <title type="short" as="introduced">Greenland Annexation and Statehood Act</title>
    <title type="official" as="introduced">To authorize the annexation and subsequent admission to statehood of Greenland, and for other purposes.</title>
  </titles>
  <sponsor bioguide_id="F000484"/>
  <cosponsors>
    <cosponsor bioguide_id="R000619" joined="2026-01-12"/>
  </cosponsors>
  <actions>
    <action datetime="2026-01-12">
      <text>Introduced in House</text>
    </action>
    <action datetime="2026-01-12" state="REFERRED">
      <text>Referred to the House Committee on Foreign Affairs.</text>
    </action>
  </actions>
  <committees>
    <committee code="HSFA" name="House Foreign Affairs" subcommittee="" activity="Referred To"/>
  </committees>
  <relatedbills/>
  <subjects/>
  <amendments/>
</bill>
