<bill session="119" type="h" number="9086" updated="2026-06-05T15:05:53Z">
  <state datetime="2026-06-02">REFERRED</state>
  <status>
    <introduced datetime="2026-06-02"/>
  </status>
  <introduced datetime="2026-06-02"/>
  <titles>
    <title type="display">Foreign Service Modernization Act</title>
    <title type="short" as="introduced">Foreign Service Modernization Act</title>
    <title type="official" as="introduced">To amend the Foreign Service Act of 1980 to modify and improve that Act.</title>
  </titles>
  <sponsor bioguide_id="L000599"/>
  <cosponsors>
    <cosponsor bioguide_id="M001199" joined="2026-06-02"/>
  </cosponsors>
  <actions>
    <action datetime="2026-06-02">
      <text>Introduced in House</text>
    </action>
    <action datetime="2026-06-02" state="REFERRED">
      <text>Referred to the Committee on Foreign Affairs, and in addition to the Committee on Ways and Means, for a period to be subsequently determined by the Speaker, in each case for consideration of such provisions as fall within the jurisdiction of the committee concerned.</text>
    </action>
    <action datetime="2026-06-02">
      <text>Referred to the Committee on Foreign Affairs, and in addition to the Committee on Ways and Means, for a period to be subsequently determined by the Speaker, in each case for consideration of such provisions as fall within the jurisdiction of the committee concerned.</text>
    </action>
  </actions>
  <committees>
    <committee code="HSWM" name="House Ways and Means" subcommittee="" activity="Referred To"/>
    <committee code="HSFA" name="House Foreign Affairs" subcommittee="" activity="Referred To"/>
  </committees>
  <relatedbills/>
  <subjects>
    <term name="International affairs"/>
  </subjects>
  <amendments/>
</bill>
