<bill session="119" type="h" number="2551" updated="2025-04-11T08:06:55Z">
  <state datetime="2025-04-01">REFERRED</state>
  <status>
    <introduced datetime="2025-04-01"/>
  </status>
  <introduced datetime="2025-04-01"/>
  <titles>
    <title type="display">Military Installation Retail Security Act of 2025</title>
    <title type="short" as="introduced">Military Installation Retail Security Act of 2025</title>
    <title type="official" as="introduced">To amend title 10, United States Code, to establish requirements relating to long-term concessions agreements between the Secretary of Defense and certain retailers, and for other purposes.</title>
  </titles>
  <sponsor bioguide_id="H001101"/>
  <cosponsors>
    <cosponsor bioguide_id="B001291" joined="2025-04-08"/>
    <cosponsor bioguide_id="B001321" joined="2025-04-09"/>
    <cosponsor bioguide_id="C001118" joined="2025-04-07"/>
    <cosponsor bioguide_id="E000300" joined="2025-04-07"/>
    <cosponsor bioguide_id="G000603" joined="2025-04-07"/>
    <cosponsor bioguide_id="G000589" joined="2025-04-08"/>
    <cosponsor bioguide_id="G000590" joined="2025-04-09"/>
    <cosponsor bioguide_id="H001098" joined="2025-04-10"/>
    <cosponsor bioguide_id="K000405" joined="2025-04-07"/>
    <cosponsor bioguide_id="O000175" joined="2025-04-07"/>
    <cosponsor bioguide_id="T000478" joined="2025-04-08"/>
  </cosponsors>
  <actions>
    <action datetime="2025-04-01">
      <text>Introduced in House</text>
    </action>
    <action datetime="2025-04-01" state="REFERRED">
      <text>Referred to the House Committee on Armed Services.</text>
    </action>
  </actions>
  <committees>
    <committee code="HSAS" name="House Armed Services" subcommittee="" activity="Referred To"/>
  </committees>
  <relatedbills/>
  <subjects/>
  <amendments/>
</bill>
