{
  "actions": [
    {
      "acted_at": "2026-05-19",
      "action_code": "Intro-H",
      "references": [],
      "text": "Introduced in House",
      "type": "action"
    },
    {
      "acted_at": "2026-05-19",
      "action_code": "H11100",
      "committees": [
        "HSWM"
      ],
      "references": [],
      "status": "REFERRED",
      "text": "Referred to the House Committee on Ways and Means.",
      "type": "referral"
    }
  ],
  "amendments": [],
  "bill_id": "hr8892-119",
  "bill_type": "hr",
  "by_request": false,
  "committee_reports": [],
  "committees": [
    {
      "activity": [
        "Referred To"
      ],
      "committee": "House Ways and Means",
      "committee_id": "HSWM"
    }
  ],
  "congress": "119",
  "cosponsors": [
    {
      "bioguide_id": "C000059",
      "district": "41",
      "name": "Calvert, Ken",
      "original_cosponsor": false,
      "sponsored_at": "2026-06-08",
      "state": "CA",
      "title": "Rep.",
      "withdrawn_at": null
    },
    {
      "bioguide_id": "K000376",
      "district": "16",
      "name": "Kelly, Mike",
      "original_cosponsor": false,
      "sponsored_at": "2026-06-08",
      "state": "PA",
      "title": "Rep.",
      "withdrawn_at": null
    },
    {
      "bioguide_id": "S001199",
      "district": "11",
      "name": "Smucker, Lloyd",
      "original_cosponsor": false,
      "sponsored_at": "2026-05-20",
      "state": "PA",
      "title": "Rep.",
      "withdrawn_at": null
    },
    {
      "bioguide_id": "V000134",
      "district": "24",
      "name": "Van Duyne, Beth",
      "original_cosponsor": false,
      "sponsored_at": "2026-06-08",
      "state": "TX",
      "title": "Rep.",
      "withdrawn_at": null
    },
    {
      "bioguide_id": "Y000067",
      "district": "2",
      "name": "Yakym, Rudy",
      "original_cosponsor": false,
      "sponsored_at": "2026-06-03",
      "state": "IN",
      "title": "Rep.",
      "withdrawn_at": null
    }
  ],
  "enacted_as": null,
  "history": {
    "active": false,
    "awaiting_signature": false,
    "enacted": false,
    "vetoed": false
  },
  "introduced_at": "2026-05-19",
  "number": "8892",
  "official_title": "To amend title XII of the Social Security Act to require States to first use certain funds to pay outstanding balances on advances made under such title prior to using such funds for any other purpose.",
  "popular_title": null,
  "related_bills": [],
  "short_title": "CAL Repayment Act",
  "sponsor": {
    "bioguide_id": "F000480",
    "district": "20",
    "name": "Fong, Vince",
    "state": "CA",
    "title": "Rep.",
    "type": "person"
  },
  "status": "REFERRED",
  "status_at": "2026-05-19",
  "subjects": [],
  "subjects_top_term": null,
  "summary": null,
  "titles": [
    {
      "as": null,
      "is_for_portion": false,
      "textVersionCode": null,
      "title": "CAL Repayment Act",
      "type": "display"
    },
    {
      "as": "introduced",
      "is_for_portion": false,
      "textVersionCode": null,
      "title": "CAL Repayment Act",
      "type": "short"
    },
    {
      "as": "introduced",
      "is_for_portion": false,
      "textVersionCode": null,
      "title": "Creating Accountability in Loan Repayment Act",
      "type": "short"
    },
    {
      "as": "introduced",
      "is_for_portion": false,
      "textVersionCode": null,
      "title": "To amend title XII of the Social Security Act to require States to first use certain funds to pay outstanding balances on advances made under such title prior to using such funds for any other purpose.",
      "type": "official"
    }
  ],
  "updated_at": "2026-06-09T08:06:46Z",
  "url": "https://www.govinfo.gov/bulkdata/BILLSTATUS/119/hr/BILLSTATUS-119hr8892.xml"
}