{
  "actions": [
    {
      "acted_at": "2026-06-01",
      "action_code": "10025",
      "committees": [
        "SSJU"
      ],
      "references": [],
      "text": "Submitted in Senate",
      "type": "action"
    },
    {
      "acted_at": "2026-06-01",
      "action_code": "",
      "committees": [
        "SSJU"
      ],
      "references": [
        {
          "reference": "CR S2479",
          "type": "text"
        }
      ],
      "status": "REFERRED",
      "text": "Referred to the Committee on the Judiciary.",
      "type": "referral"
    }
  ],
  "amendments": [],
  "bill_id": "sconres34-119",
  "bill_type": "sconres",
  "by_request": false,
  "committee_reports": [],
  "committees": [
    {
      "activity": [
        "Referred To"
      ],
      "committee": "Senate Judiciary",
      "committee_id": "SSJU"
    }
  ],
  "congress": "119",
  "cosponsors": [
    {
      "bioguide_id": "B001288",
      "district": null,
      "name": "Booker, Cory A.",
      "original_cosponsor": true,
      "sponsored_at": "2026-06-01",
      "state": "NJ",
      "title": "Sen.",
      "withdrawn_at": null
    },
    {
      "bioguide_id": "H000273",
      "district": null,
      "name": "Hickenlooper, John W.",
      "original_cosponsor": true,
      "sponsored_at": "2026-06-01",
      "state": "CO",
      "title": "Sen.",
      "withdrawn_at": null
    },
    {
      "bioguide_id": "H001042",
      "district": null,
      "name": "Hirono, Mazie K.",
      "original_cosponsor": true,
      "sponsored_at": "2026-06-01",
      "state": "HI",
      "title": "Sen.",
      "withdrawn_at": null
    },
    {
      "bioguide_id": "P000145",
      "district": null,
      "name": "Padilla, Alex",
      "original_cosponsor": true,
      "sponsored_at": "2026-06-01",
      "state": "CA",
      "title": "Sen.",
      "withdrawn_at": null
    },
    {
      "bioguide_id": "S001150",
      "district": null,
      "name": "Schiff, Adam B.",
      "original_cosponsor": true,
      "sponsored_at": "2026-06-01",
      "state": "CA",
      "title": "Sen.",
      "withdrawn_at": null
    },
    {
      "bioguide_id": "V000128",
      "district": null,
      "name": "Van Hollen, Chris",
      "original_cosponsor": true,
      "sponsored_at": "2026-06-01",
      "state": "MD",
      "title": "Sen.",
      "withdrawn_at": null
    }
  ],
  "enacted_as": null,
  "history": {
    "active": false,
    "awaiting_signature": false,
    "enacted": false,
    "vetoed": false
  },
  "introduced_at": "2026-06-01",
  "number": "34",
  "official_title": "A concurrent resolution recognizing the importance of saving lives, reducing gun violence, and strengthening public safety as the United States celebrates its 250th anniversary.",
  "popular_title": null,
  "related_bills": [
    {
      "bill_id": "hconres107-119",
      "identified_by": "CRS",
      "reason": "identical",
      "type": "bill"
    }
  ],
  "short_title": null,
  "sponsor": {
    "bioguide_id": "A000382",
    "district": null,
    "name": "Alsobrooks, Angela D.",
    "state": "MD",
    "title": "Sen.",
    "type": "person"
  },
  "status": "REFERRED",
  "status_at": "2026-06-01",
  "subjects": [
    "Crime and law enforcement"
  ],
  "subjects_top_term": "Crime and law enforcement",
  "summary": null,
  "titles": [
    {
      "as": "introduced",
      "is_for_portion": false,
      "textVersionCode": null,
      "title": "A concurrent resolution recognizing the importance of saving lives, reducing gun violence, and strengthening public safety as the United States celebrates its 250th anniversary.",
      "type": "official"
    },
    {
      "as": null,
      "is_for_portion": false,
      "textVersionCode": null,
      "title": "A concurrent resolution recognizing the importance of saving lives, reducing gun violence, and strengthening public safety as the United States celebrates its 250th anniversary.",
      "type": "display"
    }
  ],
  "updated_at": "2026-06-25T20:36:00Z",
  "url": "https://www.govinfo.gov/bulkdata/BILLSTATUS/119/sconres/BILLSTATUS-119sconres34.xml"
}