<bill session="119" type="h" number="6457" updated="2025-12-23T05:38:18Z">
  <state datetime="2025-12-04">REFERRED</state>
  <status>
    <introduced datetime="2025-12-04"/>
  </status>
  <introduced datetime="2025-12-04"/>
  <titles>
    <title type="display">FAIR Act</title>
    <title type="short" as="introduced">FAIR Act</title>
    <title type="short" as="introduced">Food Assistance Integrity and Responsibility Act</title>
    <title type="official" as="introduced">To amend the Food and Nutrition Act of 2008 to require the placement of a photograph on an electronic benefit transfer card used by a household to purchase food with supplemental nutrition assistance program benefits, and for other purposes.</title>
  </titles>
  <sponsor bioguide_id="M000194"/>
  <cosponsors>
    <cosponsor bioguide_id="B000825" joined="2025-12-04"/>
    <cosponsor bioguide_id="M001212" joined="2025-12-04"/>
  </cosponsors>
  <actions>
    <action datetime="2025-12-04">
      <text>Introduced in House</text>
    </action>
    <action datetime="2025-12-04" state="REFERRED">
      <text>Referred to the House Committee on Agriculture.</text>
    </action>
  </actions>
  <committees>
    <committee code="HSAG" name="House Agriculture" subcommittee="" activity="Referred To"/>
  </committees>
  <relatedbills/>
  <subjects/>
  <amendments/>
</bill>
