<bill session="119" type="h" number="9348" updated="2026-06-25T14:34:16Z">
  <state datetime="2026-06-18">REFERRED</state>
  <status>
    <introduced datetime="2026-06-18"/>
  </status>
  <introduced datetime="2026-06-18"/>
  <titles>
    <title type="display">Public Access Protection Act</title>
    <title type="short" as="introduced">Public Access Protection Act</title>
    <title type="official" as="introduced">To require the Secretary of the Army to include in any final recommendation for a water resources development project of the Corps of Engineers a plan to maintain equivalent levels of access to existing public recreational amenities, and for other purposes.</title>
  </titles>
  <sponsor bioguide_id="F000483"/>
  <cosponsors/>
  <actions>
    <action datetime="2026-06-18">
      <text>Introduced in House</text>
    </action>
    <action datetime="2026-06-18" state="REFERRED">
      <text>Referred to the House Committee on Transportation and Infrastructure.</text>
    </action>
  </actions>
  <committees>
    <committee code="HSPW" name="House Transportation and Infrastructure" subcommittee="" activity="Referred To"/>
  </committees>
  <relatedbills/>
  <subjects>
    <term name="Water resources development"/>
  </subjects>
  <amendments/>
</bill>
