<bill session="119" type="h" number="7285" updated="2026-02-19T04:08:25Z">
  <state datetime="2026-01-30">REFERRED</state>
  <status>
    <introduced datetime="2026-01-30"/>
  </status>
  <introduced datetime="2026-01-30"/>
  <titles>
    <title type="display">Bulletproof Law Enforcement Vehicles Act</title>
    <title type="short" as="introduced">Bulletproof Law Enforcement Vehicles Act</title>
    <title type="official" as="introduced">To amend the Homeland Security Act of 2002 to authorize the use of certain financial assistance for vehicle security enhancement upgrades, and for other purposes.</title>
  </titles>
  <sponsor bioguide_id="G000594"/>
  <cosponsors/>
  <actions>
    <action datetime="2026-01-30">
      <text>Introduced in House</text>
    </action>
    <action datetime="2026-01-30" state="REFERRED">
      <text>Referred to the House Committee on Homeland Security.</text>
    </action>
  </actions>
  <committees>
    <committee code="HSHM" name="House Homeland Security" subcommittee="" activity="Referred To"/>
  </committees>
  <relatedbills/>
  <subjects/>
  <amendments/>
</bill>
