{
  "actions": [
    {
      "acted_at": "2025-11-28",
      "action_code": "Intro-H",
      "references": [],
      "text": "Introduced in House",
      "type": "action"
    },
    {
      "acted_at": "2025-11-28",
      "action_code": "H11100",
      "committees": [
        "HSSM"
      ],
      "references": [],
      "status": "REFERRED",
      "text": "Referred to the House Committee on Small Business.",
      "type": "referral"
    }
  ],
  "amendments": [],
  "bill_id": "hr6328-119",
  "bill_type": "hr",
  "by_request": false,
  "committee_reports": [],
  "committees": [
    {
      "activity": [
        "Referred To"
      ],
      "committee": "House Small Business",
      "committee_id": "HSSM"
    }
  ],
  "congress": "119",
  "cosponsors": [
    {
      "bioguide_id": "B001327",
      "district": "8",
      "name": "Bresnahan, Robert P.",
      "original_cosponsor": true,
      "sponsored_at": "2025-11-28",
      "state": "PA",
      "title": "Rep.",
      "withdrawn_at": null
    }
  ],
  "enacted_as": null,
  "history": {
    "active": false,
    "awaiting_signature": false,
    "enacted": false,
    "vetoed": false
  },
  "introduced_at": "2025-11-28",
  "number": "6328",
  "official_title": "To require the Administrator of the Small Business Administration to carry out a pilot program for construction or management of build-to-rent multifamily housing, and for other purposes.",
  "popular_title": null,
  "related_bills": [],
  "short_title": null,
  "sponsor": {
    "bioguide_id": "V000138",
    "district": "7",
    "name": "Vindman, Eugene Simon",
    "state": "VA",
    "title": "Rep.",
    "type": "person"
  },
  "status": "REFERRED",
  "status_at": "2025-11-28",
  "subjects": [],
  "subjects_top_term": null,
  "summary": null,
  "titles": [
    {
      "as": null,
      "is_for_portion": false,
      "textVersionCode": null,
      "title": "To require the Administrator of the Small Business Administration to carry out a pilot program for construction or management of build-to-rent multifamily housing, and for other purposes.",
      "type": "display"
    },
    {
      "as": "introduced",
      "is_for_portion": false,
      "textVersionCode": null,
      "title": "To require the Administrator of the Small Business Administration to carry out a pilot program for construction or management of build-to-rent multifamily housing, and for other purposes.",
      "type": "official"
    }
  ],
  "updated_at": "2025-11-29T09:05:21Z",
  "url": "https://www.govinfo.gov/bulkdata/BILLSTATUS/119/hr/BILLSTATUS-119hr6328.xml"
}