<bill session="119" type="h" number="7148" updated="2026-01-24T09:09:14Z">
  <state datetime="2026-01-22T17:00:11-05:00">PASS_OVER:HOUSE</state>
  <status>
    <unknown datetime="2026-01-22T17:00:11-05:00"/>
  </status>
  <introduced datetime="2026-01-20"/>
  <titles>
    <title type="short" as="introduced">Consolidated Appropriations Act, 2026</title>
    <title type="short" as="introduced" partial="1">Department of Education Appropriations Act, 2026</title>
    <title type="short" as="introduced" partial="1">Department of Health and Human Services Appropriations Act, 2026</title>
    <title type="short" as="introduced" partial="1">Department of Housing and Urban Development Appropriations Act, 2026</title>
    <title type="short" as="introduced" partial="1">Department of Labor Appropriations Act, 2026</title>
    <title type="short" as="introduced" partial="1">Departments of Labor, Health and Human Services, and Education, and Related Agencies Appropriations Act, 2026</title>
    <title type="short" as="passed house">Consolidated Appropriations Act, 2026</title>
    <title type="short" as="passed house" partial="1">Department of Education Appropriations Act, 2026</title>
    <title type="short" as="passed house" partial="1">Department of Health and Human Services Appropriations Act, 2026</title>
    <title type="short" as="passed house" partial="1">Department of Housing and Urban Development Appropriations Act, 2026</title>
    <title type="short" as="passed house" partial="1">Department of Labor Appropriations Act, 2026</title>
    <title type="short" as="passed house" partial="1">Departments of Labor, Health and Human Services, and Education, and Related Agencies Appropriations Act, 2026</title>
    <title type="short" as="passed house" partial="1">National Security, Department of State, and Related Programs Appropriations Act, 2026</title>
    <title type="official" as="introduced">Making further consolidated appropriations for the fiscal year ending September 30, 2026, and for other purposes.</title>
    <title type="official">Making further consolidated appropriations for the fiscal year ending September 30, 2026, and for other purposes.</title>
    <title type="display">Consolidated Appropriations Act, 2026</title>
  </titles>
  <sponsor bioguide_id="C001053"/>
  <cosponsors/>
  <actions>
    <action datetime="2026-01-20">
      <text>Introduced in House</text>
    </action>
    <action datetime="2026-01-20" state="REFERRED">
      <text>Referred to the Committee on Appropriations, and in addition to the Committees on the Budget, and Ways and Means, for a period to be subsequently determined by the Speaker, in each case for consideration of such provisions as fall within the jurisdiction of the committee concerned.</text>
    </action>
    <action datetime="2026-01-20">
      <text>Referred to the Committee on Appropriations, and in addition to the Committees on the Budget, and Ways and Means, for a period to be subsequently determined by the Speaker, in each case for consideration of such provisions as fall within the jurisdiction of the committee concerned.</text>
    </action>
    <action datetime="2026-01-20">
      <text>Referred to the Committee on Appropriations, and in addition to the Committees on the Budget, and Ways and Means, for a period to be subsequently determined by the Speaker, in each case for consideration of such provisions as fall within the jurisdiction of the committee concerned.</text>
    </action>
    <action datetime="2026-01-22T09:03:25-05:00">
      <text>Rules Committee Resolution H. Res. 1014 Reported to House. Rule provides for consideration of H.R. 7148 and H.R. 7147. The resolution provides for consideration of H.R. 7148 under a structured rule and H.R. 7147 under a closed rule. The rule provides for one hour of debate and a motion to recommit on each bill.</text>
    </action>
    <action datetime="2026-01-22T11:54:05-05:00">
      <text>Considered under the provisions of rule H. Res. 1014.</text>
      <reference ref="CR H1185-1299" label="consideration"/>
    </action>
    <action datetime="2026-01-22T11:54:10-05:00">
      <text>Rule provides for consideration of H.R. 7148 and H.R. 7147. The resolution provides for consideration of H.R. 7148 under a structured rule and H.R. 7147 under a closed rule. The rule provides for one hour of debate and a motion to recommit on each bill.</text>
    </action>
    <action datetime="2026-01-22T11:54:33-05:00">
      <text>House resolved itself into the Committee of the Whole House on the state of the Union pursuant to H. Res. 1014 and Rule XVIII.</text>
    </action>
    <action datetime="2026-01-22T11:54:34-05:00">
      <text>The Speaker designated the Honorable Mary E. Miller to act as Chairwoman of the Committee.</text>
    </action>
    <action datetime="2026-01-22T11:54:41-05:00">
      <text>GENERAL DEBATE - The Committee of the Whole proceeded with one hour of general debate on H.R. 7148.</text>
    </action>
    <action datetime="2026-01-22T12:58:02-05:00">
      <text>DEBATE - Pursuant to the provisions of H. Res. 1014, the Committee of the Whole proceeded with 10 minutes of debate on the Massie amendment No. 1.</text>
    </action>
    <action datetime="2026-01-22T13:10:22-05:00">
      <text>POSTPONED PROCEEDINGS - At the conclusion of debate on the Massie amendment No. 1, the Chair put the question on agreeing to the amendment and by voice vote, announced the ayes had prevailed. Mr. Massie demanded a recorded vote and the Chair postponed further proceedings until a time to be announced.</text>
    </action>
    <action datetime="2026-01-22T13:11:03-05:00">
      <text>DEBATE - Pursuant to the provisions of H. Res. 1014, the Committee of the Whole proceeded with 10 minutes of debate on the Norman amendment No. 2.</text>
    </action>
    <action datetime="2026-01-22T13:24:20-05:00">
      <text>POSTPONED PROCEEDINGS - At the conclusion of debate on the Norman amendment No. 2, the Chair put the question on agreeing to the amendment and by voice vote, announced the ayes had prevailed. Ms. DeLauro demanded a recorded vote and the Chair postponed further proceedings until a time to be announced.</text>
    </action>
    <action datetime="2026-01-22T13:25:00-05:00">
      <text>Mr. Cole moved that the committee rise.</text>
    </action>
    <action datetime="2026-01-22T13:25:12-05:00">
      <text>On motion that the committee rise Agreed to by voice vote.</text>
    </action>
    <action datetime="2026-01-22T13:25:21-05:00">
      <text>Committee of the Whole House on the state of the Union rises leaving H.R. 7148 as unfinished business.</text>
    </action>
    <action datetime="2026-01-22T16:41:56-05:00">
      <text>Considered as unfinished business.</text>
      <reference ref="CR H1330-1333" label="consideration"/>
    </action>
    <action datetime="2026-01-22T16:42:28-05:00">
      <text>The House resolved into Committee of the Whole House on the state of the Union for further consideration.</text>
    </action>
    <action datetime="2026-01-22T16:51:59-05:00">
      <text>The House rose from the Committee of the Whole House on the state of the Union to report H.R. 7148.</text>
    </action>
    <action datetime="2026-01-22T16:52:46-05:00">
      <text>The previous question was ordered pursuant to the rule.</text>
    </action>
    <vote how="roll" type="vote" roll="45" datetime="2026-01-22T17:00:11-05:00" where="h" result="pass" state="PASS_OVER:HOUSE">
      <text>On passage Passed by the Yeas and Nays: 341 - 88 (Roll No. 45).</text>
      <reference ref="CR H1193-1297" label="text of amendment in the nature of a substitute"/>
    </vote>
    <action datetime="2026-01-22T17:00:13-05:00">
      <text>Motion to reconsider laid on the table Agreed to without objection.</text>
    </action>
  </actions>
  <committees>
    <committee code="HSWM" name="House Ways and Means" subcommittee="" activity="Referred To"/>
    <committee code="HSBU" name="House Budget" subcommittee="" activity="Referred To"/>
    <committee code="HSAP" name="House Appropriations" subcommittee="" activity="Referred To"/>
  </committees>
  <relatedbills>
    <bill session="119" type="s" number="2572" relation="unknown"/>
    <bill session="119" type="s" number="2587" relation="unknown"/>
    <bill session="119" type="h" number="4317" relation="unknown"/>
    <bill session="119" type="h" number="5304" relation="unknown"/>
    <bill session="119" type="h" number="4552" relation="unknown"/>
    <bill session="119" type="h" number="5281" relation="unknown"/>
    <bill session="119" type="s" number="2465" relation="unknown"/>
    <bill session="119" type="s" number="339" relation="unknown"/>
    <bill session="119" type="s" number="882" relation="unknown"/>
    <bill session="119" type="h" number="4016" relation="unknown"/>
    <bill session="119" type="s" number="932" relation="unknown"/>
    <bill session="119" type="h" number="2450" relation="unknown"/>
    <bill session="119" type="s" number="3302" relation="unknown"/>
    <bill session="119" type="s" number="2237" relation="unknown"/>
    <bill session="119" type="s" number="532" relation="unknown"/>
    <bill session="119" type="h" number="1197" relation="unknown"/>
    <bill session="119" type="h" number="1262" relation="unknown"/>
    <bill session="119" type="h" number="5064" relation="unknown"/>
    <bill session="119" type="h" number="1843" relation="unknown"/>
    <bill session="119" type="s" number="2743" relation="unknown"/>
    <bill session="119" type="s" number="1302" relation="unknown"/>
    <bill session="119" type="h" number="4313" relation="unknown"/>
    <bill session="119" type="h" number="842" relation="unknown"/>
    <bill session="119" type="h" number="6504" relation="unknown"/>
    <bill session="119" type="h" number="1794" relation="unknown"/>
    <bill session="119" type="s" number="2497" relation="unknown"/>
    <bill session="119" type="h" number="1509" relation="unknown"/>
    <bill session="119" type="s" number="752" relation="unknown"/>
    <bill session="119" type="h" number="6500" relation="unknown"/>
    <bill session="119" type="h" number="1625" relation="unknown"/>
    <bill session="119" type="h" number="5259" relation="unknown"/>
    <bill session="119" type="s" number="266" relation="unknown"/>
    <bill session="119" type="h" number="628" relation="unknown"/>
    <bill session="119" type="hr" number="1014" relation="unknown"/>
    <bill session="119" type="h" number="1796" relation="unknown"/>
    <bill session="119" type="h" number="2092" relation="unknown"/>
    <bill session="119" type="h" number="4993" relation="unknown"/>
    <bill session="119" type="h" number="929" relation="unknown"/>
    <bill session="119" type="s" number="735" relation="unknown"/>
    <bill session="119" type="h" number="5574" relation="unknown"/>
    <bill session="119" type="s" number="742" relation="unknown"/>
    <bill session="119" type="s" number="2751" relation="unknown"/>
    <bill session="119" type="h" number="2822" relation="unknown"/>
    <bill session="119" type="s" number="1015" relation="unknown"/>
  </relatedbills>
  <subjects>
    <term name="Economics and public finance"/>
  </subjects>
  <amendments>
    <amendment number="h159"/>
    <amendment number="h156"/>
    <amendment number="h155"/>
  </amendments>
  <summary date="2026-01-22T13:40:18Z" status="Introduced in House"></summary>
</bill>
