<bill session="119" type="h" number="4970" updated="2025-08-16T08:05:27Z">
  <state datetime="2025-08-15">REFERRED</state>
  <status>
    <introduced datetime="2025-08-15"/>
  </status>
  <introduced datetime="2025-08-15"/>
  <titles>
    <title type="display">To amend the Reclamation States Emergency Drought Relief Act of 1991 to facilitate the transfer of water from the Orland Project to the Central Valley Project.</title>
    <title type="official" as="introduced">To amend the Reclamation States Emergency Drought Relief Act of 1991 to facilitate the transfer of water from the Orland Project to the Central Valley Project.</title>
  </titles>
  <sponsor bioguide_id="L000578"/>
  <cosponsors/>
  <actions>
    <action datetime="2025-08-15">
      <text>Introduced in House</text>
    </action>
    <action datetime="2025-08-15" state="REFERRED">
      <text>Referred to the House Committee on Natural Resources.</text>
    </action>
  </actions>
  <committees>
    <committee code="HSII" name="House Natural Resources" subcommittee="" activity="Referred To"/>
  </committees>
  <relatedbills/>
  <subjects/>
  <amendments/>
</bill>
