<bill session="119" type="h" number="6736" updated="2025-12-17T09:06:07Z">
  <state datetime="2025-12-16">REFERRED</state>
  <status>
    <introduced datetime="2025-12-16"/>
  </status>
  <introduced datetime="2025-12-16"/>
  <titles>
    <title type="display">To require the transfer of regulatory control of certain munitions exports from the Department of Commerce to the Department of State, and for other purposes.</title>
    <title type="official" as="introduced">To require the transfer of regulatory control of certain munitions exports from the Department of Commerce to the Department of State, and for other purposes.</title>
  </titles>
  <sponsor bioguide_id="C001091"/>
  <cosponsors>
    <cosponsor bioguide_id="C001127" joined="2025-12-16"/>
    <cosponsor bioguide_id="D000631" joined="2025-12-16"/>
    <cosponsor bioguide_id="D000216" joined="2025-12-16"/>
    <cosponsor bioguide_id="F000476" joined="2025-12-16"/>
    <cosponsor bioguide_id="G000599" joined="2025-12-16"/>
    <cosponsor bioguide_id="G000606" joined="2025-12-16"/>
    <cosponsor bioguide_id="J000298" joined="2025-12-16"/>
    <cosponsor bioguide_id="K000385" joined="2025-12-16"/>
    <cosponsor bioguide_id="M001223" joined="2025-12-16"/>
    <cosponsor bioguide_id="M000312" joined="2025-12-16"/>
    <cosponsor bioguide_id="M001226" joined="2025-12-16"/>
    <cosponsor bioguide_id="O000173" joined="2025-12-16"/>
    <cosponsor bioguide_id="R000617" joined="2025-12-16"/>
    <cosponsor bioguide_id="T000468" joined="2025-12-16"/>
    <cosponsor bioguide_id="T000474" joined="2025-12-16"/>
    <cosponsor bioguide_id="V000081" joined="2025-12-16"/>
    <cosponsor bioguide_id="W000797" joined="2025-12-16"/>
  </cosponsors>
  <actions>
    <action datetime="2025-12-16">
      <text>Introduced in House</text>
    </action>
    <action datetime="2025-12-16" state="REFERRED">
      <text>Referred to the House Committee on Foreign Affairs.</text>
    </action>
  </actions>
  <committees>
    <committee code="HSFA" name="House Foreign Affairs" subcommittee="" activity="Referred To"/>
  </committees>
  <relatedbills/>
  <subjects/>
  <amendments/>
</bill>
