{
  "actions": [
    {
      "acted_at": "2025-12-18",
      "action_code": "1025",
      "references": [],
      "text": "Submitted in House",
      "type": "action"
    },
    {
      "acted_at": "2025-12-18",
      "action_code": "B00100",
      "references": [
        {
          "reference": "CR E1228",
          "type": null
        }
      ],
      "text": "Sponsor introductory remarks on measure.",
      "type": "action"
    },
    {
      "acted_at": "2025-12-18",
      "action_code": "H11100",
      "references": [],
      "text": "Submitted in House",
      "type": "action"
    },
    {
      "acted_at": "2025-12-18",
      "action_code": "H11100",
      "committees": [
        "HSGO"
      ],
      "references": [],
      "status": "REFERRED",
      "text": "Referred to the House Committee on Oversight and Government Reform.",
      "type": "referral"
    }
  ],
  "amendments": [],
  "bill_id": "hres968-119",
  "bill_type": "hres",
  "by_request": false,
  "committee_reports": [],
  "committees": [
    {
      "activity": [
        "Referred To"
      ],
      "committee": "House Oversight and Government Reform",
      "committee_id": "HSGO"
    }
  ],
  "congress": "119",
  "cosponsors": [],
  "enacted_as": null,
  "history": {
    "active": true,
    "active_at": "2025-12-18",
    "awaiting_signature": false,
    "enacted": false,
    "vetoed": false
  },
  "introduced_at": "2025-12-18",
  "number": "968",
  "official_title": "Recognizing the 90th anniversary of the National Council of Negro Women and honoring its historic legacy and continued service to the Nation.",
  "popular_title": null,
  "related_bills": [],
  "short_title": null,
  "sponsor": {
    "bioguide_id": "W000187",
    "district": "43",
    "name": "Waters, Maxine",
    "state": "CA",
    "title": "Rep.",
    "type": "person"
  },
  "status": "REFERRED",
  "status_at": "2025-12-18",
  "subjects": [
    "Civil rights and liberties, minority issues"
  ],
  "subjects_top_term": "Civil rights and liberties, minority issues",
  "summary": null,
  "titles": [
    {
      "as": "introduced",
      "is_for_portion": false,
      "textVersionCode": null,
      "title": "Recognizing the 90th anniversary of the National Council of Negro Women and honoring its historic legacy and continued service to the Nation.",
      "type": "official"
    },
    {
      "as": null,
      "is_for_portion": false,
      "textVersionCode": null,
      "title": "Recognizing the 90th anniversary of the National Council of Negro Women and honoring its historic legacy and continued service to the Nation.",
      "type": "display"
    }
  ],
  "updated_at": "2026-01-05T15:42:20Z",
  "url": "https://www.govinfo.gov/bulkdata/BILLSTATUS/119/hres/BILLSTATUS-119hres968.xml"
}