{
  "actions": [
    {
      "acted_at": "2026-03-10",
      "action_code": "10000",
      "references": [],
      "text": "Introduced in Senate",
      "type": "action"
    },
    {
      "acted_at": "2026-03-10",
      "action_code": "",
      "committees": [
        "SSFI"
      ],
      "references": [],
      "status": "REFERRED",
      "text": "Read twice and referred to the Committee on Finance.",
      "type": "referral"
    }
  ],
  "amendments": [],
  "bill_id": "s4038-119",
  "bill_type": "s",
  "by_request": false,
  "committee_reports": [],
  "committees": [
    {
      "activity": [
        "Referred To"
      ],
      "committee": "Senate Finance",
      "committee_id": "SSFI"
    }
  ],
  "congress": "119",
  "cosponsors": [
    {
      "bioguide_id": "G000555",
      "district": null,
      "name": "Gillibrand, Kirsten E.",
      "original_cosponsor": true,
      "sponsored_at": "2026-03-10",
      "state": "NY",
      "title": "Sen.",
      "withdrawn_at": null
    },
    {
      "bioguide_id": "H000273",
      "district": null,
      "name": "Hickenlooper, John W.",
      "original_cosponsor": true,
      "sponsored_at": "2026-03-10",
      "state": "CO",
      "title": "Sen.",
      "withdrawn_at": null
    },
    {
      "bioguide_id": "H001042",
      "district": null,
      "name": "Hirono, Mazie K.",
      "original_cosponsor": true,
      "sponsored_at": "2026-03-10",
      "state": "HI",
      "title": "Sen.",
      "withdrawn_at": null
    },
    {
      "bioguide_id": "K000367",
      "district": null,
      "name": "Klobuchar, Amy",
      "original_cosponsor": true,
      "sponsored_at": "2026-03-10",
      "state": "MN",
      "title": "Sen.",
      "withdrawn_at": null
    },
    {
      "bioguide_id": "R000608",
      "district": null,
      "name": "Rosen, Jacky",
      "original_cosponsor": true,
      "sponsored_at": "2026-03-10",
      "state": "NV",
      "title": "Sen.",
      "withdrawn_at": null
    },
    {
      "bioguide_id": "S000148",
      "district": null,
      "name": "Schumer, Charles E.",
      "original_cosponsor": true,
      "sponsored_at": "2026-03-10",
      "state": "NY",
      "title": "Sen.",
      "withdrawn_at": null
    },
    {
      "bioguide_id": "V000128",
      "district": null,
      "name": "Van Hollen, Chris",
      "original_cosponsor": true,
      "sponsored_at": "2026-03-10",
      "state": "MD",
      "title": "Sen.",
      "withdrawn_at": null
    }
  ],
  "enacted_as": null,
  "history": {
    "active": false,
    "awaiting_signature": false,
    "enacted": false,
    "vetoed": false
  },
  "introduced_at": "2026-03-10",
  "number": "4038",
  "official_title": "A bill to exempt small business concerns from duties imposed by the President under section 122 of the Trade Act of 1974 and to prevent price gouging with respect to goods subject to such duties.",
  "popular_title": null,
  "related_bills": [],
  "short_title": "Small Business Liberation 2.0 Act",
  "sponsor": {
    "bioguide_id": "M000133",
    "district": null,
    "name": "Markey, Edward J.",
    "state": "MA",
    "title": "Sen.",
    "type": "person"
  },
  "status": "REFERRED",
  "status_at": "2026-03-10",
  "subjects": [],
  "subjects_top_term": null,
  "summary": null,
  "titles": [
    {
      "as": "introduced",
      "is_for_portion": false,
      "textVersionCode": null,
      "title": "A bill to exempt small business concerns from duties imposed by the President under section 122 of the Trade Act of 1974 and to prevent price gouging with respect to goods subject to such duties.",
      "type": "official"
    },
    {
      "as": null,
      "is_for_portion": false,
      "textVersionCode": null,
      "title": "Small Business Liberation 2.0 Act",
      "type": "display"
    },
    {
      "as": "introduced",
      "is_for_portion": false,
      "textVersionCode": null,
      "title": "Small Business Liberation 2.0 Act",
      "type": "short"
    }
  ],
  "updated_at": "2026-03-24T05:18:30Z",
  "url": "https://www.govinfo.gov/bulkdata/BILLSTATUS/119/s/BILLSTATUS-119s4038.xml"
}