<bill session="119" type="hr" number="1030" updated="2026-02-03T09:05:56Z">
  <state datetime="2026-02-02">REFERRED</state>
  <status>
    <introduced datetime="2026-02-02"/>
  </status>
  <introduced datetime="2026-02-02"/>
  <titles>
    <title type="display">To end ICE abuse.</title>
    <title type="official" as="introduced">To end ICE abuse.</title>
  </titles>
  <sponsor bioguide_id="K000389"/>
  <cosponsors/>
  <actions>
    <action datetime="2026-02-02">
      <text>Submitted in House</text>
    </action>
    <action datetime="2026-02-02" state="REFERRED">
      <text>Referred to the Committee on the Judiciary, and in addition to the Committees on Homeland Security, and Ways and Means, for a period to be subsequently determined by the Speaker, in each case for consideration of such provisions as fall within the jurisdiction of the committee concerned.</text>
    </action>
    <action datetime="2026-02-02">
      <text>Referred to the Committee on the Judiciary, and in addition to the Committees on Homeland Security, and Ways and Means, for a period to be subsequently determined by the Speaker, in each case for consideration of such provisions as fall within the jurisdiction of the committee concerned.</text>
    </action>
    <action datetime="2026-02-02">
      <text>Referred to the Committee on the Judiciary, and in addition to the Committees on Homeland Security, and Ways and Means, for a period to be subsequently determined by the Speaker, in each case for consideration of such provisions as fall within the jurisdiction of the committee concerned.</text>
    </action>
  </actions>
  <committees>
    <committee code="HSWM" name="House Ways and Means" subcommittee="" activity="Referred To"/>
    <committee code="HSHM" name="House Homeland Security" subcommittee="" activity="Referred To"/>
    <committee code="HSJU" name="House Judiciary" subcommittee="" activity="Referred To"/>
  </committees>
  <relatedbills/>
  <subjects/>
  <amendments/>
</bill>
