{
  "actions": [
    {
      "acted_at": "2025-02-06",
      "action_code": "10000",
      "references": [],
      "text": "Introduced in Senate",
      "type": "action"
    },
    {
      "acted_at": "2025-02-06",
      "action_code": "",
      "committees": [
        "SSEG"
      ],
      "references": [],
      "status": "REFERRED",
      "text": "Read twice and referred to the Committee on Energy and Natural Resources.",
      "type": "referral"
    },
    {
      "acted_at": "2025-12-09",
      "action_code": "",
      "committee": "Committee on Energy and Natural Resources Subcommittee on National Parks",
      "committees": [
        "SSEG"
      ],
      "references": [],
      "text": "Committee on Energy and Natural Resources Subcommittee on National Parks. Hearings held.",
      "type": "hearings"
    },
    {
      "acted_at": "2026-02-04",
      "action_code": "",
      "committees": [
        "SSEG"
      ],
      "references": [],
      "status": "REPORTED",
      "text": "Committee on Energy and Natural Resources. Ordered to be reported with an amendment in the nature of a substitute favorably and an amendment to the title.",
      "type": "ordered-reported"
    }
  ],
  "amendments": [],
  "bill_id": "s446-119",
  "bill_type": "s",
  "by_request": false,
  "committee_reports": [],
  "committees": [
    {
      "activity": [
        "Markup By",
        "Referred To"
      ],
      "committee": "Senate Energy and Natural Resources",
      "committee_id": "SSEG"
    },
    {
      "activity": [
        "Hearings By (subcommittee)"
      ],
      "committee": "Senate Energy and Natural Resources",
      "committee_id": "SSEG",
      "subcommittee": "Subcommittee on National Parks",
      "subcommittee_id": "04"
    }
  ],
  "congress": "119",
  "cosponsors": [],
  "enacted_as": null,
  "history": {
    "active": true,
    "active_at": "2025-12-09",
    "awaiting_signature": false,
    "enacted": false,
    "vetoed": false
  },
  "introduced_at": "2025-02-06",
  "number": "446",
  "official_title": "A bill to prohibit Big Cypress National Preserve from being designated as wilderness or as a component of the National Wilderness Preservation System, and for other purposes.",
  "popular_title": null,
  "related_bills": [
    {
      "bill_id": "hr1192-119",
      "identified_by": "CRS",
      "reason": "related",
      "type": "bill"
    }
  ],
  "short_title": null,
  "sponsor": {
    "bioguide_id": "S001217",
    "district": null,
    "name": "Scott, Rick",
    "state": "FL",
    "title": "Sen.",
    "type": "person"
  },
  "status": "REPORTED",
  "status_at": "2026-02-04",
  "subjects": [
    "Florida",
    "Parks, recreation areas, trails",
    "Public lands and natural resources",
    "Wilderness and natural areas, wildlife refuges, wild rivers, habitats"
  ],
  "subjects_top_term": "Public lands and natural resources",
  "summary": {
    "as": "Introduced in Senate",
    "asOf": "2025-02-06",
    "date": "2026-02-09T17:07:22Z",
    "text": ""
  },
  "titles": [
    {
      "as": "introduced",
      "is_for_portion": false,
      "textVersionCode": null,
      "title": "A bill to prohibit Big Cypress National Preserve from being designated as wilderness or as a component of the National Wilderness Preservation System, and for other purposes.",
      "type": "official"
    },
    {
      "as": null,
      "is_for_portion": false,
      "textVersionCode": null,
      "title": "A bill to prohibit Big Cypress National Preserve from being designated as wilderness or as a component of the National Wilderness Preservation System, and for other purposes.",
      "type": "display"
    }
  ],
  "updated_at": "2026-02-09T17:08:09Z",
  "url": "https://www.govinfo.gov/bulkdata/BILLSTATUS/119/s/BILLSTATUS-119s446.xml"
}