{
  "actions": [
    {
      "acted_at": "2025-02-04",
      "action_code": "10000",
      "references": [],
      "text": "Introduced in Senate",
      "type": "action"
    },
    {
      "acted_at": "2025-02-04",
      "action_code": "",
      "committees": [
        "SSHR"
      ],
      "references": [],
      "status": "REFERRED",
      "text": "Read twice and referred to the Committee on Health, Education, Labor, and Pensions.",
      "type": "referral"
    }
  ],
  "amendments": [],
  "bill_id": "s380-119",
  "bill_type": "s",
  "by_request": false,
  "committee_reports": [],
  "committees": [
    {
      "activity": [
        "Referred To"
      ],
      "committee": "Senate Health, Education, Labor, and Pensions",
      "committee_id": "SSHR"
    }
  ],
  "congress": "119",
  "cosponsors": [
    {
      "bioguide_id": "B001319",
      "district": null,
      "name": "Britt, Katie Boyd",
      "original_cosponsor": true,
      "sponsored_at": "2025-02-04",
      "state": "AL",
      "title": "Sen.",
      "withdrawn_at": null
    },
    {
      "bioguide_id": "C001035",
      "district": null,
      "name": "Collins, Susan M.",
      "original_cosponsor": true,
      "sponsored_at": "2025-02-04",
      "state": "ME",
      "title": "Sen.",
      "withdrawn_at": null
    },
    {
      "bioguide_id": "S001203",
      "district": null,
      "name": "Smith, Tina",
      "original_cosponsor": true,
      "sponsored_at": "2025-02-04",
      "state": "MN",
      "title": "Sen.",
      "withdrawn_at": null
    }
  ],
  "enacted_as": null,
  "history": {
    "active": false,
    "awaiting_signature": false,
    "enacted": false,
    "vetoed": false
  },
  "introduced_at": "2025-02-04",
  "number": "380",
  "official_title": "A bill to improve obstetric emergency care.",
  "popular_title": null,
  "related_bills": [],
  "short_title": null,
  "sponsor": {
    "bioguide_id": "H001076",
    "district": null,
    "name": "Hassan, Margaret Wood",
    "state": "NH",
    "title": "Sen.",
    "type": "person"
  },
  "status": "REFERRED",
  "status_at": "2025-02-04",
  "subjects": [],
  "subjects_top_term": null,
  "summary": null,
  "titles": [
    {
      "as": null,
      "is_for_portion": false,
      "textVersionCode": null,
      "title": "A bill to improve obstetric emergency care.",
      "type": "display"
    },
    {
      "as": "introduced",
      "is_for_portion": false,
      "textVersionCode": null,
      "title": "A bill to improve obstetric emergency care.",
      "type": "official"
    }
  ],
  "updated_at": "2025-02-05T11:56:21Z",
  "url": "https://www.govinfo.gov/bulkdata/BILLSTATUS/119/s/BILLSTATUS-119s380.xml"
}