<bill session="119" type="s" number="4564" updated="2026-06-16T21:05:30Z">
  <state datetime="2026-05-19">REFERRED</state>
  <status>
    <introduced datetime="2026-05-19"/>
  </status>
  <introduced datetime="2026-05-19"/>
  <titles>
    <title type="display">Maritime Cybersecurity Act</title>
    <title type="short" as="introduced">Maritime Cybersecurity Act</title>
    <title type="official" as="introduced">A bill to amend title 46, United States Code, to require the Secretary of the department in which the Coast Guard is operating to assess cybersecurity risks of certain software and hardware used in certain maritime facilities, and for other purposes.</title>
  </titles>
  <sponsor bioguide_id="S001217"/>
  <cosponsors>
    <cosponsor bioguide_id="K000394" joined="2026-05-19"/>
  </cosponsors>
  <actions>
    <action datetime="2026-05-19">
      <text>Introduced in Senate</text>
    </action>
    <action datetime="2026-05-19" state="REFERRED">
      <text>Read twice and referred to the Committee on Commerce, Science, and Transportation.</text>
    </action>
  </actions>
  <committees>
    <committee code="SSCM" name="Senate Commerce, Science, and Transportation" subcommittee="" activity="Referred To"/>
  </committees>
  <relatedbills/>
  <subjects>
    <term name="Transportation and public works"/>
  </subjects>
  <amendments/>
</bill>
