<bill session="119" type="h" number="8346" updated="2026-04-21T21:53:04Z">
  <state datetime="2026-04-16">REFERRED</state>
  <status>
    <introduced datetime="2026-04-16"/>
  </status>
  <introduced datetime="2026-04-16"/>
  <titles>
    <title type="display">Foreign Service Age and Integration and Reform (FAIR) Act of 2026</title>
    <title type="short" as="introduced">Foreign Service Age and Integration and Reform (FAIR) Act of 2026</title>
    <title type="official" as="introduced">To raise the Foreign Service mandatory retirement age by aligning it with the Social Security Full Retirement Age, and for other purposes.</title>
  </titles>
  <sponsor bioguide_id="O000176"/>
  <cosponsors>
    <cosponsor bioguide_id="L000599" joined="2026-04-16"/>
  </cosponsors>
  <actions>
    <action datetime="2026-04-16">
      <text>Introduced in House</text>
    </action>
    <action datetime="2026-04-16" state="REFERRED">
      <text>Referred to the House Committee on Foreign Affairs.</text>
    </action>
  </actions>
  <committees>
    <committee code="HSFA" name="House Foreign Affairs" subcommittee="" activity="Referred To"/>
  </committees>
  <relatedbills>
    <bill session="119" type="s" number="4002" relation="unknown"/>
  </relatedbills>
  <subjects>
    <term name="Government operations and politics"/>
  </subjects>
  <amendments/>
</bill>
