<bill session="119" type="sr" number="606" updated="2026-02-12T19:20:26Z">
  <state datetime="2026-02-11">REFERRED</state>
  <status>
    <introduced datetime="2026-02-11"/>
  </status>
  <introduced datetime="2026-02-11"/>
  <titles>
    <title type="display">A resolution condemning the Government of Iran for its suppression of the right of Iranians to peacefully assemble.</title>
    <title type="official" as="introduced">A resolution condemning the Government of Iran for its suppression of the right of Iranians to peacefully assemble.</title>
  </titles>
  <sponsor bioguide_id="L000575"/>
  <cosponsors>
    <cosponsor bioguide_id="B001288" joined="2026-02-11"/>
    <cosponsor bioguide_id="B001236" joined="2026-02-11"/>
    <cosponsor bioguide_id="B001319" joined="2026-02-11"/>
    <cosponsor bioguide_id="B001305" joined="2026-02-11"/>
    <cosponsor bioguide_id="C001047" joined="2026-02-11"/>
    <cosponsor bioguide_id="C001095" joined="2026-02-11"/>
    <cosponsor bioguide_id="C001096" joined="2026-02-11"/>
    <cosponsor bioguide_id="C001098" joined="2026-02-11"/>
    <cosponsor bioguide_id="D000563" joined="2026-02-11"/>
    <cosponsor bioguide_id="E000295" joined="2026-02-11"/>
    <cosponsor bioguide_id="F000463" joined="2026-02-11"/>
    <cosponsor bioguide_id="G000386" joined="2026-02-11"/>
    <cosponsor bioguide_id="H001061" joined="2026-02-11"/>
    <cosponsor bioguide_id="K000384" joined="2026-02-11"/>
    <cosponsor bioguide_id="K000394" joined="2026-02-11"/>
    <cosponsor bioguide_id="M000355" joined="2026-02-11"/>
    <cosponsor bioguide_id="M001176" joined="2026-02-11"/>
    <cosponsor bioguide_id="M001190" joined="2026-02-11"/>
    <cosponsor bioguide_id="R000618" joined="2026-02-11"/>
    <cosponsor bioguide_id="R000608" joined="2026-02-11"/>
    <cosponsor bioguide_id="S000148" joined="2026-02-11"/>
    <cosponsor bioguide_id="S001181" joined="2026-02-11"/>
    <cosponsor bioguide_id="S001198" joined="2026-02-11"/>
    <cosponsor bioguide_id="V000128" joined="2026-02-11"/>
  </cosponsors>
  <actions>
    <action datetime="2026-02-11">
      <text>Submitted in Senate</text>
    </action>
    <action datetime="2026-02-11" state="REFERRED">
      <text>Referred to the Committee on Foreign Relations.</text>
      <reference ref="CR S582" label="text"/>
    </action>
  </actions>
  <committees>
    <committee code="SSFR" name="Senate Foreign Relations" subcommittee="" activity="Referred To"/>
  </committees>
  <relatedbills/>
  <subjects/>
  <amendments/>
</bill>
