{
  "actions": [
    {
      "acted_at": "2026-06-24",
      "action_code": "10000",
      "references": [],
      "text": "Introduced in Senate",
      "type": "action"
    },
    {
      "acted_at": "2026-06-24",
      "action_code": "",
      "committees": [
        "SSEV"
      ],
      "references": [
        {
          "reference": "CR S3206-3214",
          "type": "text"
        }
      ],
      "status": "REFERRED",
      "text": "Read twice and referred to the Committee on Environment and Public Works.",
      "type": "referral"
    }
  ],
  "amendments": [],
  "bill_id": "s4944-119",
  "bill_type": "s",
  "by_request": false,
  "committee_reports": [],
  "committees": [
    {
      "activity": [
        "Referred To"
      ],
      "committee": "Senate Environment and Public Works",
      "committee_id": "SSEV"
    }
  ],
  "congress": "119",
  "cosponsors": [
    {
      "bioguide_id": "B001319",
      "district": null,
      "name": "Britt, Katie Boyd",
      "original_cosponsor": true,
      "sponsored_at": "2026-06-24",
      "state": "AL",
      "title": "Sen.",
      "withdrawn_at": null
    },
    {
      "bioguide_id": "L000571",
      "district": null,
      "name": "Lummis, Cynthia M.",
      "original_cosponsor": true,
      "sponsored_at": "2026-06-24",
      "state": "WY",
      "title": "Sen.",
      "withdrawn_at": null
    },
    {
      "bioguide_id": "S001217",
      "district": null,
      "name": "Scott, Rick",
      "original_cosponsor": true,
      "sponsored_at": "2026-06-24",
      "state": "FL",
      "title": "Sen.",
      "withdrawn_at": null
    }
  ],
  "enacted_as": null,
  "history": {
    "active": false,
    "awaiting_signature": false,
    "enacted": false,
    "vetoed": false
  },
  "introduced_at": "2026-06-24",
  "number": "4944",
  "official_title": "A bill to streamline permitting under the Natural Gas Act, the Federal Water Pollution Control Act, and the National Environmental Policy Act of 1969, and for other purposes.",
  "popular_title": null,
  "related_bills": [],
  "short_title": null,
  "sponsor": {
    "bioguide_id": "A000383",
    "district": null,
    "name": "Armstrong, Alan",
    "state": "OK",
    "title": "Sen.",
    "type": "person"
  },
  "status": "REFERRED",
  "status_at": "2026-06-24",
  "subjects": [],
  "subjects_top_term": null,
  "summary": null,
  "titles": [
    {
      "as": null,
      "is_for_portion": false,
      "textVersionCode": null,
      "title": "A bill to streamline permitting under the Natural Gas Act, the Federal Water Pollution Control Act, and the National Environmental Policy Act of 1969, and for other purposes.",
      "type": "display"
    },
    {
      "as": "introduced",
      "is_for_portion": false,
      "textVersionCode": null,
      "title": "A bill to streamline permitting under the Natural Gas Act, the Federal Water Pollution Control Act, and the National Environmental Policy Act of 1969, and for other purposes.",
      "type": "official"
    }
  ],
  "updated_at": "2026-06-26T18:11:16Z",
  "url": "https://www.govinfo.gov/bulkdata/BILLSTATUS/119/s/BILLSTATUS-119s4944.xml"
}