<bill session="119" type="s" number="4778" updated="2026-06-23T22:07:44Z">
  <state datetime="2026-06-11">REFERRED</state>
  <status>
    <introduced datetime="2026-06-11"/>
  </status>
  <introduced datetime="2026-06-11"/>
  <titles>
    <title type="short" as="introduced">Postsecondary Student Success Act of 2026</title>
    <title type="display">Postsecondary Student Success Act of 2026</title>
    <title type="official" as="introduced">A bill to authorize the Secretary of Education to award grants to create evidence-based student success programs designed to increase participation, retention, and completion rates of high-need students.</title>
  </titles>
  <sponsor bioguide_id="H001046"/>
  <cosponsors>
    <cosponsor bioguide_id="C001088" joined="2026-06-11"/>
  </cosponsors>
  <actions>
    <action datetime="2026-06-11">
      <text>Introduced in Senate</text>
    </action>
    <action datetime="2026-06-11" state="REFERRED">
      <text>Read twice and referred to the Committee on Health, Education, Labor, and Pensions.</text>
    </action>
  </actions>
  <committees>
    <committee code="SSHR" name="Senate Health, Education, Labor, and Pensions" subcommittee="" activity="Referred To"/>
  </committees>
  <relatedbills/>
  <subjects>
    <term name="Education"/>
  </subjects>
  <amendments/>
</bill>
