<bill session="119" type="h" number="8501" updated="2026-04-28T08:05:49Z">
  <state datetime="2026-04-27">REFERRED</state>
  <status>
    <introduced datetime="2026-04-27"/>
  </status>
  <introduced datetime="2026-04-27"/>
  <titles>
    <title type="display">To amend the Internal Revenue Code of 1986 to allow rehabilitation expenditures for public school buildings to qualify for rehabilitation credit.</title>
    <title type="official" as="introduced">To amend the Internal Revenue Code of 1986 to allow rehabilitation expenditures for public school buildings to qualify for rehabilitation credit.</title>
  </titles>
  <sponsor bioguide_id="E000296"/>
  <cosponsors>
    <cosponsor bioguide_id="D000096" joined="2026-04-27"/>
    <cosponsor bioguide_id="M001160" joined="2026-04-27"/>
    <cosponsor bioguide_id="N000147" joined="2026-04-27"/>
    <cosponsor bioguide_id="S001205" joined="2026-04-27"/>
    <cosponsor bioguide_id="S001145" joined="2026-04-27"/>
  </cosponsors>
  <actions>
    <action datetime="2026-04-27">
      <text>Introduced in House</text>
    </action>
    <action datetime="2026-04-27" state="REFERRED">
      <text>Referred to the House Committee on Ways and Means.</text>
    </action>
  </actions>
  <committees>
    <committee code="HSWM" name="House Ways and Means" subcommittee="" activity="Referred To"/>
  </committees>
  <relatedbills/>
  <subjects/>
  <amendments/>
</bill>
