{
  "actions": [
    {
      "acted_at": "2026-02-02",
      "action_code": "",
      "committee": "Agriculture, Nutrition, and Forestry",
      "committees": [
        "SSAF"
      ],
      "references": [],
      "status": "REPORTED",
      "text": "Committee on Agriculture, Nutrition, and Forestry. Original measure reported to Senate by Senator Boozman. Without written report.",
      "type": "reported"
    },
    {
      "acted_at": "2026-02-02",
      "action_code": "",
      "calendar": "Senate Legislative",
      "number": "312",
      "references": [],
      "text": "Placed on Senate Legislative Calendar under General Orders. Calendar No. 312.",
      "type": "calendar",
      "under": "General Orders"
    }
  ],
  "amendments": [],
  "bill_id": "s3755-119",
  "bill_type": "s",
  "by_request": false,
  "committee_reports": [],
  "committees": [
    {
      "activity": [
        "Reported Original Measure"
      ],
      "committee": "Senate Agriculture, Nutrition, and Forestry",
      "committee_id": "SSAF"
    }
  ],
  "congress": "119",
  "cosponsors": [],
  "enacted_as": null,
  "history": {
    "active": true,
    "active_at": "2026-02-02",
    "awaiting_signature": false,
    "enacted": false,
    "vetoed": false
  },
  "introduced_at": "2026-02-02",
  "number": "3755",
  "official_title": "An original bill to provide for a system of regulation of the offer and sale of digital commodities by the Commodity Futures Trading Commission, and for other purposes.",
  "popular_title": null,
  "related_bills": [],
  "short_title": "Digital Commodity Intermediaries Act",
  "sponsor": {
    "bioguide_id": "B001236",
    "district": null,
    "name": "Boozman, John",
    "state": "AR",
    "title": "Sen.",
    "type": "person"
  },
  "status": "REPORTED",
  "status_at": "2026-02-02",
  "subjects": [
    "Finance and financial sector"
  ],
  "subjects_top_term": "Finance and financial sector",
  "summary": null,
  "titles": [
    {
      "as": null,
      "is_for_portion": false,
      "textVersionCode": null,
      "title": "Digital Commodity Intermediaries Act",
      "type": "display"
    },
    {
      "as": "reported to senate",
      "is_for_portion": false,
      "textVersionCode": null,
      "title": "Digital Commodity Intermediaries Act",
      "type": "short"
    },
    {
      "as": "introduced",
      "is_for_portion": false,
      "textVersionCode": null,
      "title": "An original bill to provide for a system of regulation of the offer and sale of digital commodities by the Commodity Futures Trading Commission, and for other purposes.",
      "type": "official"
    }
  ],
  "updated_at": "2026-02-06T12:40:10Z",
  "url": "https://www.govinfo.gov/bulkdata/BILLSTATUS/119/s/BILLSTATUS-119s3755.xml"
}