<bill session="119" type="h" number="8362" updated="2026-04-21T08:05:52Z">
  <state datetime="2026-04-16">REFERRED</state>
  <status>
    <introduced datetime="2026-04-16"/>
  </status>
  <introduced datetime="2026-04-16"/>
  <titles>
    <title type="display">To amend sections 5314 and 5339 of title 49, United States Code, to allow for the use of a portion of grants available for buses and bus-related equipment and facilities to be used for workforce development and training, and for other purposes.</title>
    <title type="official" as="introduced">To amend sections 5314 and 5339 of title 49, United States Code, to allow for the use of a portion of grants available for buses and bus-related equipment and facilities to be used for workforce development and training, and for other purposes.</title>
  </titles>
  <sponsor bioguide_id="W000808"/>
  <cosponsors>
    <cosponsor bioguide_id="B001285" joined="2026-04-16"/>
    <cosponsor bioguide_id="D000530" joined="2026-04-16"/>
    <cosponsor bioguide_id="E000296" joined="2026-04-20"/>
    <cosponsor bioguide_id="F000481" joined="2026-04-16"/>
    <cosponsor bioguide_id="F000477" joined="2026-04-16"/>
    <cosponsor bioguide_id="F000483" joined="2026-04-16"/>
    <cosponsor bioguide_id="F000476" joined="2026-04-16"/>
    <cosponsor bioguide_id="G000559" joined="2026-04-16"/>
    <cosponsor bioguide_id="G000586" joined="2026-04-16"/>
    <cosponsor bioguide_id="H001094" joined="2026-04-16"/>
    <cosponsor bioguide_id="H001068" joined="2026-04-16"/>
    <cosponsor bioguide_id="J000309" joined="2026-04-16"/>
    <cosponsor bioguide_id="J000288" joined="2026-04-16"/>
    <cosponsor bioguide_id="M001196" joined="2026-04-16"/>
    <cosponsor bioguide_id="N000002" joined="2026-04-16"/>
    <cosponsor bioguide_id="N000147" joined="2026-04-16"/>
    <cosponsor bioguide_id="P000614" joined="2026-04-16"/>
    <cosponsor bioguide_id="P000621" joined="2026-04-16"/>
    <cosponsor bioguide_id="R000579" joined="2026-04-16"/>
    <cosponsor bioguide_id="S001159" joined="2026-04-16"/>
    <cosponsor bioguide_id="T000468" joined="2026-04-16"/>
  </cosponsors>
  <actions>
    <action datetime="2026-04-16">
      <text>Introduced in House</text>
    </action>
    <action datetime="2026-04-16" state="REFERRED">
      <text>Referred to the House Committee on Transportation and Infrastructure.</text>
    </action>
  </actions>
  <committees>
    <committee code="HSPW" name="House Transportation and Infrastructure" subcommittee="" activity="Referred To"/>
  </committees>
  <relatedbills/>
  <subjects/>
  <amendments/>
</bill>
