{
  "actions": [
    {
      "acted_at": "2025-06-04",
      "action_code": "Intro-H",
      "references": [],
      "text": "Introduced in House",
      "type": "action"
    },
    {
      "acted_at": "2025-06-04",
      "action_code": "H11100",
      "committees": [
        "HSPW"
      ],
      "references": [],
      "status": "REFERRED",
      "text": "Referred to the House Committee on Transportation and Infrastructure.",
      "type": "referral"
    }
  ],
  "amendments": [],
  "bill_id": "hr3738-119",
  "bill_type": "hr",
  "by_request": false,
  "committee_reports": [],
  "committees": [
    {
      "activity": [
        "Referred To"
      ],
      "committee": "House Transportation and Infrastructure",
      "committee_id": "HSPW"
    }
  ],
  "congress": "119",
  "cosponsors": [
    {
      "bioguide_id": "L000599",
      "district": "17",
      "name": "Lawler, Michael",
      "original_cosponsor": true,
      "sponsored_at": "2025-06-04",
      "state": "NY",
      "title": "Rep.",
      "withdrawn_at": null
    }
  ],
  "enacted_as": null,
  "history": {
    "active": false,
    "awaiting_signature": false,
    "enacted": false,
    "vetoed": false
  },
  "introduced_at": "2025-06-04",
  "number": "3738",
  "official_title": "To amend the Robert T. Stafford Disaster Relief and Emergency Assistance Act to provide for assistance to States and local governments in response to extreme heat events, and for other purposes.",
  "popular_title": null,
  "related_bills": [],
  "short_title": "Heat Management Assistance Grant Act of 2025",
  "sponsor": {
    "bioguide_id": "S001211",
    "district": "4",
    "name": "Stanton, Greg",
    "state": "AZ",
    "title": "Rep.",
    "type": "person"
  },
  "status": "REFERRED",
  "status_at": "2025-06-04",
  "subjects": [],
  "subjects_top_term": null,
  "summary": null,
  "titles": [
    {
      "as": null,
      "is_for_portion": false,
      "textVersionCode": null,
      "title": "HMAG Act of 2025",
      "type": "display"
    },
    {
      "as": "introduced",
      "is_for_portion": false,
      "textVersionCode": null,
      "title": "Heat Management Assistance Grant Act of 2025",
      "type": "short"
    },
    {
      "as": "introduced",
      "is_for_portion": false,
      "textVersionCode": null,
      "title": "HMAG Act of 2025",
      "type": "short"
    },
    {
      "as": "introduced",
      "is_for_portion": false,
      "textVersionCode": null,
      "title": "To amend the Robert T. Stafford Disaster Relief and Emergency Assistance Act to provide for assistance to States and local governments in response to extreme heat events, and for other purposes.",
      "type": "official"
    }
  ],
  "updated_at": "2025-06-13T06:53:18Z",
  "url": "https://www.govinfo.gov/bulkdata/BILLSTATUS/119/hr/BILLSTATUS-119hr3738.xml"
}